{
  "title": {
    "en": "Yield between times is !{{less|more}} than",
    "de": "Ertrag zwischen Zeiten ist !{{weniger|mehr}} als",
    "nl": "Opbrengst tussen tijden is !{{minder|meer}} dan",
    "fr": "Le rendement entre les heures est !{{inférieur|supérieur}} à",
    "it": "Il rendimento tra gli orari è !{{inferiore|superiore}} a",
    "sv": "Avkastning mellan tider är !{{mindre|mer}} än",
    "no": "Avkastning mellom tider er !{{mindre|mer}} enn",
    "da": "Udbytte mellem tider er !{{mindre|mere}} end",
    "es": "El rendimiento entre horas es !{{menor|mayor}} que",
    "pl": "Uzysk między czasami jest !{{mniejszy|większy}} niż",
    "ru": "Доход между временем !{{меньше|больше}} чем",
    "ko": "시간 사이 수익이 다음보다 !{{적음|많음}}",
    "ar": "العائد بين الأوقات !{{أقل|أكثر}} من"
  },
  "titleFormatted": {
    "en": "Yield between [[start_time]] and [[end_time]] is !{{less|more}} than [[value]] kWh",
    "de": "Ertrag zwischen [[start_time]] und [[end_time]] ist !{{weniger|mehr}} als [[value]] kWh",
    "nl": "Opbrengst tussen [[start_time]] en [[end_time]] is !{{minder|meer}} dan [[value]] kWh",
    "fr": "Le rendement entre [[start_time]] et [[end_time]] est !{{inférieur|supérieur}} à [[value]] kWh",
    "it": "Il rendimento tra [[start_time]] e [[end_time]] è !{{inferiore|superiore}} a [[value]] kWh",
    "sv": "Avkastning mellan [[start_time]] och [[end_time]] är !{{mindre|mer}} än [[value]] kWh",
    "no": "Avkastning mellom [[start_time]] og [[end_time]] er !{{mindre|mer}} enn [[value]] kWh",
    "da": "Udbytte mellem [[start_time]] og [[end_time]] er !{{mindre|mere}} end [[value]] kWh",
    "es": "El rendimiento entre [[start_time]] y [[end_time]] es !{{menor|mayor}} que [[value]] kWh",
    "pl": "Uzysk między [[start_time]] a [[end_time]] jest !{{mniejszy|większy}} niż [[value]] kWh",
    "ru": "Доход между [[start_time]] и [[end_time]] !{{меньше|больше}} чем [[value]] кВтч",
    "ko": "[[start_time]]와 [[end_time]] 사이 수익이 [[value]] kWh보다 !{{적음|많음}}",
    "ar": "العائد بين [[start_time]] و [[end_time]] !{{أقل|أكثر}} من [[value]] كيلوواط ساعة"
  },
  "highlight": true,
  "args": [
    {
      "type": "device",
      "name": "device",
      "filter": "driver_id=solar"
    },
    {
      "type": "time",
      "name": "start_time",
      "required": true
    },
    {
      "type": "time",
      "name": "end_time",
      "required": true
    },
    {
      "type": "number",
      "name": "value",
      "required": true,
      "min": 0,
      "step": 0.1
    }
  ]
}