{
  "title": {
    "en": "Set a new variable markup",
    "de": "Neuen variablen Aufschlag festlegen",
    "nl": "Stel een nieuwe variabele opslag in"
  },
  "titleFormatted": {
    "en": "Set variable markup to [[value]]%",
    "de": "Variablen Aufschlag einstellen auf [[value]]€",
    "nl": "Stel variabele opslag in op [[value]]%"
  },
  "highlight": true,
  "args": [
    {
      "type": "device",
      "name": "device",
      "filter": "driver_id=dap"
    },
    {
      "name": "value",
      "type": "number",
      "placeholder": {
        "en": "Variable markup (%)",
        "de": "Variabler Aufschlag (%)",
        "nl": "Variabele opslag (%)"
      }
    }
  ]
}
